{
    "blogtxt": "https://themes.getnikola.com/v7/blogtxt.zip",
    "bnw": "https://themes.getnikola.com/v7/bnw.zip",
    "bootblog": "https://themes.getnikola.com/v7/bootblog.zip",
    "bootblog-jinja": "https://themes.getnikola.com/v7/bootblog-jinja.zip",
    "bootstrap": "https://themes.getnikola.com/v7/bootstrap.zip",
    "bootstrap-jinja": "https://themes.getnikola.com/v7/bootstrap-jinja.zip",
    "bootstrap3-gradients": "https://themes.getnikola.com/v7/bootstrap3-gradients.zip",
    "bootstrap3-gradients-jinja": "https://themes.getnikola.com/v7/bootstrap3-gradients-jinja.zip",
    "cadair": "https://themes.getnikola.com/v7/cadair.zip",
    "canterville": "https://themes.getnikola.com/v7/canterville.zip",
    "carpet": "https://themes.getnikola.com/v7/carpet.zip",
    "detox": "https://themes.getnikola.com/v7/detox.zip",
    "foundation6": "https://themes.getnikola.com/v7/foundation6.zip",
    "hack": "https://themes.getnikola.com/v7/hack.zip",
    "hemingway": "https://themes.getnikola.com/v7/hemingway.zip",
    "hpstr": "https://themes.getnikola.com/v7/hpstr.zip",
    "hyde": "https://themes.getnikola.com/v7/hyde.zip",
    "jidn": "https://themes.getnikola.com/v7/jidn.zip",
    "lanyon": "https://themes.getnikola.com/v7/lanyon.zip",
    "libretto": "https://themes.getnikola.com/v7/libretto.zip",
    "lotabout": "https://themes.getnikola.com/v7/lotabout.zip",
    "material-theme": "https://themes.getnikola.com/v7/material-theme.zip",
    "maupassant": "https://themes.getnikola.com/v7/maupassant.zip",
    "mdl": "https://themes.getnikola.com/v7/mdl.zip",
    "monospace": "https://themes.getnikola.com/v7/monospace.zip",
    "oldfashioned": "https://themes.getnikola.com/v7/oldfashioned.zip",
    "planetoid": "https://themes.getnikola.com/v7/planetoid.zip",
    "readable": "https://themes.getnikola.com/v7/readable.zip",
    "reveal": "https://themes.getnikola.com/v7/reveal.zip",
    "reveal-jinja": "https://themes.getnikola.com/v7/reveal-jinja.zip",
    "slidemenu": "https://themes.getnikola.com/v7/slidemenu.zip",
    "srcco.de": "https://themes.getnikola.com/v7/srcco.de.zip",
    "yesplease": "https://themes.getnikola.com/v7/yesplease.zip",
    "zen": "https://themes.getnikola.com/v7/zen.zip",
    "zen-forkawesome": "https://themes.getnikola.com/v7/zen-forkawesome.zip",
    "zen-ipython": "https://themes.getnikola.com/v7/zen-ipython.zip",
    "zen-jinja": "https://themes.getnikola.com/v7/zen-jinja.zip"
}
